csquery/__init__.py
csquery/lucene.py
csquery/structured.py
csquery-0.1.4.dist-info/DESCRIPTION.rst
csquery-0.1.4.dist-info/METADATA
csquery-0.1.4.dist-info/metadata.json
csquery-0.1.4.dist-info/pbr.json
csquery-0.1.4.dist-info/RECORD
csquery-0.1.4.dist-info/top_level.txt
csquery-0.1.4.dist-info/WHEEL
