Metadata-Version: 2.0
Name: csquery
Version: 0.1.4
Summary: A simple query builder for Amazon Cloudsearch structured query parser.
Home-page: https://github.com/tell-k/csquery
Author: tell-k
Author-email: ffk2005 at gmail.com
License: MIT
Keywords: aws amazon cloudsearch querybuilder structured
Platform: UNKNOWN
Classifier: Development Status :: 3 - Alpha
Classifier: Environment :: Console
Classifier: Intended Audience :: Developers
Classifier: License :: OSI Approved :: MIT License
Classifier: Programming Language :: Python :: 2
Classifier: Programming Language :: Python :: 2.7
Classifier: Programming Language :: Python :: 3
Classifier: Programming Language :: Python :: 3.3
Classifier: Programming Language :: Python :: 3.4
Classifier: Programming Language :: Python :: Implementation :: CPython
Classifier: Programming Language :: Python :: Implementation :: PyPy
Classifier: Topic :: Internet :: WWW/HTTP
Classifier: Topic :: Internet :: WWW/HTTP :: Indexing/Search
Classifier: Topic :: Software Development :: Libraries
Requires-Dist: six
